.DS_Store
secrets2env.py
secrets2env-0.1.4.dist-info/METADATA
secrets2env-0.1.4.dist-info/RECORD
secrets2env-0.1.4.dist-info/WHEEL
secrets2env-0.1.4.dist-info/entry_points.txt
secrets2env-0.1.4.dist-info/top_level.txt
