Metadata-Version: 2.1
Name: secrets2env
Version: 0.1.4
Summary: Command-line tool for generating environment variables from AWS Secrets
Home-page: https://github.com/eguven/secrets2env
Maintainer: Eren Güven
Maintainer-email: erengueven0@gmail.com
License: MIT
Keywords: aws secrets environment deployment
Platform: UNKNOWN
Classifier: Development Status :: 3 - Alpha
Classifier: Intended Audience :: Developers
Classifier: Intended Audience :: Information Technology
Classifier: Intended Audience :: System Administrators
Classifier: License :: OSI Approved :: MIT License
Classifier: Operating System :: MacOS :: MacOS X
Classifier: Operating System :: POSIX :: Linux
Classifier: Programming Language :: Python
Classifier: Topic :: Security
Classifier: Topic :: Utilities
Requires-Dist: boto3 (>=1.7.6)
Requires-Dist: PyYAML
